odoo/addons/stock_quant_reservation_info/README.rst
odoo/addons/stock_quant_reservation_info/__init__.py
odoo/addons/stock_quant_reservation_info/__manifest__.py
odoo/addons/stock_quant_reservation_info/i18n/it.po
odoo/addons/stock_quant_reservation_info/i18n/stock_quant_reservation_info.pot
odoo/addons/stock_quant_reservation_info/models/__init__.py
odoo/addons/stock_quant_reservation_info/models/stock_move_line.py
odoo/addons/stock_quant_reservation_info/models/stock_quant.py
odoo/addons/stock_quant_reservation_info/readme/CONTRIBUTORS.md
odoo/addons/stock_quant_reservation_info/readme/DESCRIPTION.md
odoo/addons/stock_quant_reservation_info/readme/USAGE.md
odoo/addons/stock_quant_reservation_info/static/description/icon.png
odoo/addons/stock_quant_reservation_info/static/description/index.html
odoo/addons/stock_quant_reservation_info/views/stock_move_line.xml
odoo/addons/stock_quant_reservation_info/views/stock_quant.xml
odoo_addon_stock_quant_reservation_info-18.0.1.0.0.2.dist-info/METADATA
odoo_addon_stock_quant_reservation_info-18.0.1.0.0.2.dist-info/WHEEL
odoo_addon_stock_quant_reservation_info-18.0.1.0.0.2.dist-info/top_level.txt
odoo_addon_stock_quant_reservation_info-18.0.1.0.0.2.dist-info/RECORD
